{"authors": [], "date_download": "2021-08-12 13:54:31", "date_modify": "2021-08-12 13:54:31", "date_publish": "2020-02-05 17:44:55", "description": "The review will examine the government's handling of a long-running pay dispute with Manx teachers.", "filename": "news_world-europe-isle-of-man-51373095_1628776471.html", "image_url": "https://ichef.bbci.co.uk/news/1024/branded_news/16B29/production/_105196929_teacherwithkidsbooks.jpg", "language": "en", "localpath": "D:\\news_set/data/2021/08/06/bbc.com/news_world-europe-isle-of-man-51373095_1628776471.html", "title": "Manx teacher's pay dispute faces independent review", "title_page": "Manx teacher's pay dispute faces independent review - BBC News", "title_rss": "NULL", "source_domain": "bbc.com", "maintext": "Chief Minister Howard Quayle said he had \"every confidence\" in Mr Cregeen but that an independent body would be appointed to examine \"governance arrangements\" within the department and how it \"interacts with the schools\".", "url": "https://www.bbc.com/news/world-europe-isle-of-man-51373095"}