{"authors": [], "date_download": "2021-08-08 12:22:12", "date_modify": "2021-08-08 12:22:12", "date_publish": "2020-09-26 00:22:10", "description": "There is mounting pressure to have two of France's best-loved poets reinterred in the Paris Pantheon.", "filename": "news_world-europe-54293974_1628425332.html", "image_url": "https://ichef.bbci.co.uk/news/1024/branded_news/14D02/production/_114605258_311d9aa4-3748-434d-bba7-49e5de4adb91.jpg", "language": "en", "localpath": "D:\\news_set/data/2021/08/06/bbc.com/news_world-europe-54293974_1628425332.html", "title": "Rimbaud and Verlaine: France agonises over digging up gay poets", "title_page": "Rimbaud and Verlaine: France agonises over digging up gay poets - BBC News", "title_rss": "NULL", "source_domain": "bbc.com", "maintext": "Rimbaud and Verlaine are certainly among the most revered of French poets - and it is also true that of the 75 residents of the Pantheon, none is there for poetry. Victor Hugo was transferred for his political achievement.", "url": "https://www.bbc.com/news/world-europe-54293974"}