{"authors": [], "date_download": "2021-08-14 04:10:25", "date_modify": "2021-08-14 04:10:25", "date_publish": "2020-01-26 14:40:06", "description": "Police investigating the deaths of the McGinley siblings say the results are not being published.", "filename": "news_world-europe-51256150_1628914225.html", "image_url": "https://ichef.bbci.co.uk/news/1024/branded_news/17AB0/production/_110644969_newscastlephotoofchildrenandfather.jpg", "language": "en", "localpath": "D:\\news_set/data/2021/08/14/bbc.com/news_world-europe-51256150_1628914225.html", "title": "Dublin child deaths: McGinley children post-mortems completed", "title_page": "Dublin child deaths: McGinley children post-mortems completed - BBC News", "title_rss": "NULL", "source_domain": "bbc.com", "maintext": "Garda¨ª (Irish police) have said they not looking for anyone else in relation to the incident and described it as \"an enormous tragedy for the family\".", "url": "https://www.bbc.com/news/world-europe-51256150"}