{"authors": [], "date_download": "2021-08-07 13:46:22", "date_modify": "2021-08-07 13:46:22", "date_publish": "2020-11-13 09:52:19", "description": "On high alert, France is mourning the 130 people murdered in co-ordinated attacks five years ago.", "filename": "news_world-europe-54924051_1628343982.html", "image_url": "https://ichef.bbci.co.uk/news/1024/branded_news/93FF/production/_115478873_mediaitem115478872.jpg", "language": "en", "localpath": "D:\\news_set/data/2021/08/06/bbc.com/news_world-europe-54924051_1628343982.html", "title": "Paris attacks: France remembers night of terror amid jihadist threat", "title_page": "Paris attacks: France remembers night of terror amid jihadist threat - BBC News", "title_rss": "NULL", "source_domain": "bbc.com", "maintext": "Eagles of Death Metal lead singer Jesse Hughes has spoken of how he almost \"became French\" on the night of the Bataclan attack. \"I can almost feel the physical presence of those people I love so much - those who died, who were wounded, who survived, who helped and all their families,\" he told Le Parisien.", "url": "https://www.bbc.com/news/world-europe-54924051"}