{"authors": [], "date_download": "2021-08-08 00:48:02", "date_modify": "2021-08-08 00:48:02", "date_publish": "2020-07-25 15:40:09", "description": "The two-seater microlight hits the roof of the large house in the city of Wesel, causing a fire.", "filename": "news_world-europe-53539010_1628383682.html", "image_url": "https://ichef.bbci.co.uk/news/1024/branded_news/CBB0/production/_113644125_mediaitem113644124.jpg", "language": "en", "localpath": "D:\\news_set/data/2021/08/06/bbc.com/news_world-europe-53539010_1628383682.html", "title": "German crash: Three die as aircraft hits home in Wesel", "title_page": "German crash: Three die as aircraft hits home in Wesel - BBC News", "title_rss": "NULL", "source_domain": "bbc.com", "maintext": "Police chief Peter Reuters said emergency services were called at 14:42 local time (12.42 GMT), adding: \"Three deceased people were found in the attic of the apartment building. They are adults. A child was also slightly injured and shocked. The microlight aircraft had taken off from the Marl airfield with two occupants and landed again in Wesel for a stopover.\"", "url": "https://www.bbc.com/news/world-europe-53539010"}