{"authors": [], "date_download": "2021-08-06 13:40:34", "date_modify": "2021-08-06 13:40:34", "date_publish": "2020-06-04 14:28:44", "description": "The ban will begin on Friday following the driest spring on the island for 35 years.", "filename": "news_world-europe-isle-of-man-52909652_1628257234.html", "image_url": "https://ichef.bbci.co.uk/news/1024/branded_news/415B/production/_112713761_gettyimages-674747508-1.jpg", "language": "en", "localpath": "D:\\news_set/data/2021/08/06/bbc.com/news_world-europe-isle-of-man-52909652_1628257234.html", "title": "Hosepipe ban introduced on Isle of Man after record dry spring", "title_page": "Hosepipe ban introduced on Isle of Man after record dry spring - BBC News", "title_rss": "NULL", "source_domain": "bbc.com", "maintext": "Figures from the island's Met Office show rainfall of just 78.7mm between the start of March and the end of May, compared to a long-term average of 172mm.", "url": "https://www.bbc.com/news/world-europe-isle-of-man-52909652"}