{"authors": [], "date_download": "2021-08-18 09:35:08", "date_modify": "2021-08-18 09:35:08", "date_publish": "2020-01-04 20:31:09", "description": "The weapons were found as part of a search by garda drugs and organised crime units", "filename": "news_world-europe-50995162_1629279308.html", "image_url": "https://ichef.bbci.co.uk/news/1024/branded_news/16E99/production/_110394839_doc_9503a.jpg", "language": "en", "localpath": "D:\\news_set/data/2021/08/18/bbc.com/news_world-europe-50995162_1629279308.html", "title": "County Dublin: Ten firearms and ammunition seized", "title_page": "County Dublin: Ten firearms and ammunition seized - BBC News", "title_rss": "NULL", "source_domain": "bbc.com", "maintext": "The search, carried out by the Garda National Drugs and Organised Crime Bureau on Friday, was part of ongoing investigations.", "url": "https://www.bbc.com/news/world-europe-50995162"}