{"authors": [], "date_download": "2021-08-09 17:21:50", "date_modify": "2021-08-09 17:21:50", "date_publish": "2020-08-17 15:03:42", "description": "President Marcelo Rebelo de Sousa assists the women as their kayak capsizes amid strong currents.", "filename": "news_world-europe-53810463_1628529710.html", "image_url": "https://ichef.bbci.co.uk/news/1024/branded_news/143B3/production/_113976828_de27.jpg", "language": "en", "localpath": "D:\\news_set/data/2021/08/06/bbc.com/news_world-europe-53810463_1628529710.html", "title": "Portugal president helps rescue two women in trouble at sea", "title_page": "Portugal president helps rescue two women in trouble at sea - BBC News", "title_rss": "NULL", "source_domain": "bbc.com", "maintext": "\"As there is a very large west current, they were dragged out, turned around, swallowed a lot of water and were not even able to turn [the kayak], nor to climb [on it], or swim, such is the strength of the current,\" he told local media.", "url": "https://www.bbc.com/news/world-europe-53810463"}