{"authors": [], "date_download": "2021-08-12 06:51:34", "date_modify": "2021-08-12 06:51:34", "date_publish": "2020-02-07 13:46:31", "description": "Voters on 12 small islands make their mark 24 hours ahead of the polls opening on the mainland.", "filename": "news_world-europe-51411956_1628751094.html", "image_url": "https://ichef.bbci.co.uk/news/1024/branded_news/11FEF/production/_110811737_pollingstation.jpg", "language": "en", "localpath": "D:\\news_set/data/2021/08/06/bbc.com/news_world-europe-51411956_1628751094.html", "title": "Irish election: Islands go to the polls", "title_page": "Irish election: Islands go to the polls - BBC News", "title_rss": "NULL", "source_domain": "bbc.com", "maintext": "Legislation is in the process of being passed to allow them to vote on the same day as the rest of the country.", "url": "https://www.bbc.com/news/world-europe-51411956"}