{"authors": [], "date_download": "2021-08-07 20:01:32", "date_modify": "2021-08-07 20:01:32", "date_publish": "2020-11-06 13:53:58", "description": "Prosecutors say seven held at Charles de Gaulle airport tried to sell fake test certificates.", "filename": "news_world-europe-54839434_1628366492.html", "image_url": "https://ichef.bbci.co.uk/news/1024/branded_news/B546/production/_115260464_mediaitem115260004.jpg", "language": "en", "localpath": "D:\\news_set/data/2021/08/06/bbc.com/news_world-europe-54839434_1628366492.html", "title": "Coronavirus: Fake test certificate gang foiled at Paris airport", "title_page": "Coronavirus: Fake test certificate gang foiled at Paris airport - BBC News", "title_rss": "NULL", "source_domain": "bbc.com", "maintext": "The seven had been running an unlicensed business as luggage-wrappers, but that had suffered when passenger numbers crashed in the coronavirus pandemic, AFP news agency reported, quoting an airport source.", "url": "https://www.bbc.com/news/world-europe-54839434"}