{"authors": [], "date_download": "2021-08-06 18:07:44", "date_modify": "2021-08-06 18:07:44", "date_publish": "2020-07-30 18:24:28", "description": "Ireland's acting chief medical officer warns new figures show \"how quickly Covid-19 can remerge\".", "filename": "news_world-europe-53597179_1628273264.html", "image_url": "https://ichef.bbci.co.uk/news/1024/branded_news/BAC4/production/_113321874_test.jpg", "language": "en", "localpath": "D:\\news_set/data/2021/08/06/bbc.com/news_world-europe-53597179_1628273264.html", "title": "Coronavirus: One death and 85 new Covid-19 cases in Ireland", "title_page": "Coronavirus: One death and 85 new Covid-19 cases in Ireland - BBC News", "title_rss": "NULL", "source_domain": "bbc.com", "maintext": "It also reported that there are links between the factory cluster and clusters in direct provision centres - facilities which are used as temporary accommodation for refugees and asylum seekers.", "url": "https://www.bbc.com/news/world-europe-53597179"}