{"authors": [], "date_download": "2021-08-08 00:37:31", "date_modify": "2021-08-08 00:37:31", "date_publish": "2020-06-29 15:38:54", "description": "President Andrzej Duda comes top but fails to take enough votes to win the election outright.", "filename": "news_world-europe-53215106_1628383051.html", "image_url": "https://ichef.bbci.co.uk/news/1024/branded_news/C1D8/production/_113142694_tv062186914.jpg", "language": "en", "localpath": "D:\\news_set/data/2021/08/06/bbc.com/news_world-europe-53215106_1628383051.html", "title": "Poland presidential election heads for second round", "title_page": "Poland presidential election heads for second round - BBC News", "title_rss": "NULL", "source_domain": "bbc.com", "maintext": "Polityka weekly says Andrzej Duda's performance augurs well for the incumbent president: \"There has never been a time when a candidate with such an advantage in the first round went on to lose in the second.\"", "url": "https://www.bbc.com/news/world-europe-53215106"}