{"authors": [], "date_download": "2021-08-13 05:55:28", "date_modify": "2021-08-13 05:55:28", "date_publish": "2020-01-31 13:37:07", "description": "The father of the victims, aged three, seven and nine, says their family will be \"forever heartbroken\".", "filename": "news_world-europe-51328681_1628834128.html", "image_url": "https://ichef.bbci.co.uk/news/1024/branded_news/1F08/production/_110644970_newscastlephotoofchildrenandfather.jpg", "language": "en", "localpath": "D:\\news_set/data/2021/08/13/bbc.com/news_world-europe-51328681_1628834128.html", "title": "McGinley children killed at home mourned at Dublin funeral", "title_page": "McGinley children killed at home mourned at Dublin funeral - BBC News", "title_rss": "NULL", "source_domain": "bbc.com", "maintext": "\"We as a family are heartbroken. It will only be with your help, support and friendship that we will be able to patch our hearts together in some way, but we will still be forever heartbroken,\" he said.", "url": "https://www.bbc.com/news/world-europe-51328681"}