{"authors": [], "date_download": "2021-08-08 00:34:27", "date_modify": "2021-08-08 00:34:27", "date_publish": "2020-07-25 16:55:35", "description": "One man was arrested following the death of a man in his 70s outside a house in Dublin.", "filename": "news_world-europe-53538396_1628382867.html", "image_url": "https://ichef.bbci.co.uk/news/1024/branded_news/142BA/production/_106981628_gardai-generic.jpg", "language": "en", "localpath": "D:\\news_set/data/2021/08/06/bbc.com/news_world-europe-53538396_1628382867.html", "title": "Man dies after stabbing in Dublin", "title_page": "Man dies after stabbing in Dublin - BBC News", "title_rss": "NULL", "source_domain": "bbc.com", "maintext": "Garda¨ª (Irish police) said they responded to reports of an assault outside a house in the Whitechapel Road area of Clonsilla, at about 05:55 local time on Saturday.", "url": "https://www.bbc.com/news/world-europe-53538396"}