{"authors": [], "date_download": "2021-08-08 06:48:06", "date_modify": "2021-08-08 06:48:06", "date_publish": "2020-09-20 12:36:12", "description": "The rare \"medicane\" storm flooded buildings, toppled trees and triggered landslides in central areas.", "filename": "news_world-europe-54219180_1628405286.html", "image_url": "https://ichef.bbci.co.uk/news/1024/branded_news/529D/production/_114494112_tv063404887.jpg", "language": "en", "localpath": "D:\\news_set/data/2021/08/06/bbc.com/news_world-europe-54219180_1628405286.html", "title": "Cyclone Ianos: Three dead as 'medicane' sweeps across Greece", "title_page": "Cyclone Ianos: Three dead as 'medicane' sweeps across Greece - BBC News", "title_rss": "NULL", "source_domain": "bbc.com", "maintext": "A boat believed to be carrying 55 migrants off the western Peloponnese was also reported to be in distress on Friday. However, the Greek coast guard told AFP news agency that the boat may have changed course after receiving no help.", "url": "https://www.bbc.com/news/world-europe-54219180"}