{"authors": [], "date_download": "2021-08-08 13:52:31", "date_modify": "2021-08-08 13:52:31", "date_publish": "2020-03-12 17:45:29", "description": "Foreign Minister Luigi Di Maio hopes his country will be first in Europe to get over the emergency.", "filename": "news_world-europe-51852320_1628430751.html", "image_url": "https://ichef.bbci.co.uk/news/1024/branded_news/17BBE/production/_111241279_dimaio.jpg", "language": "en", "localpath": "D:\\news_set/data/2021/08/06/bbc.com/news_world-europe-51852320_1628430751.html", "title": "Coronavirus: Italy says 1,000 have died but lockdown can work", "title_page": "Coronavirus: Italy says 1,000 have died but lockdown can work - BBC News", "title_rss": "NULL", "source_domain": "bbc.com", "maintext": "\"We need oxygen units, and we have started production with factories that produce them or others that can adapt to start producing them,\" said Mr Di Maio. \"We're in contact with countries across the world, many of them are willing to supply us with equipment.\"", "url": "https://www.bbc.com/news/world-europe-51852320"}