{"authors": [], "date_download": "2021-08-09 11:59:05", "date_modify": "2021-08-09 11:59:05", "date_publish": "2020-10-09 22:41:57", "description": "Sophie P¨¦tronin, one of four hostages released this week, alerted French officials to the killing.", "filename": "news_world-europe-54488190_1628510345.html", "image_url": "https://ichef.bbci.co.uk/news/1024/branded_news/1313F/production/_114834187_7dda6ee2-eea0-4ddd-9dd8-8c54cdb6a466.jpg", "language": "en", "localpath": "D:\\news_set/data/2021/08/06/bbc.com/news_world-europe-54488190_1628510345.html", "title": "Mali hostages: Swiss woman killed last month", "title_page": "Mali hostages: Swiss woman killed last month - BBC News", "title_rss": "NULL", "source_domain": "bbc.com", "maintext": "It added that officials \"are making every effort to find out more about the circumstances of the killing and the whereabouts of the remains\", and that the ministry has demanded that the body be handed over.", "url": "https://www.bbc.com/news/world-europe-54488190"}