{"authors": [], "date_download": "2021-08-08 21:13:57", "date_modify": "2021-08-08 21:13:57", "date_publish": "2020-10-21 16:12:47", "description": "Two teenagers were allegedly paid hundreds of euros to point out the teacher before he was killed.", "filename": "news_world-europe-54625270_1628457237.html", "image_url": "https://ichef.bbci.co.uk/news/1024/branded_news/93C7/production/_115013873_tv063919865.jpg", "language": "en", "localpath": "D:\\news_set/data/2021/08/06/bbc.com/news_world-europe-54625270_1628457237.html", "title": 