{"authors": [], "date_download": "2021-08-08 00:25:04", "date_modify": "2021-08-08 00:25:04", "date_publish": "2020-05-04 08:00:00", "description": "News, reaction and information about the impact of coronavirus on the Bailiwick of Guernsey.", "filename": "news_live_world-europe-guernsey-52528538_1628382304.html", "image_url": "https://m.files.bbci.co.uk/modules/bbc-morph-news-waf-page-meta/5.1.0/bbc_news_logo.png", "language": "en", "localpath": "D:\\news_set/data/2021/08/06/bbc.com/news_live_world-europe-guernsey-52528538_1628382304.html", "title": "Coronavirus: Guernsey updates 4-7 May", "title_page": "Coronavirus: Guernsey updates 4-7 May - BBC News", "title_rss": "NULL", "source_domain": "bbc.com", "maintext": "Guernsey's care homes will form the front line of Guernsey's expanded testing regime, Dr Nicola Brink said.\nThe director of Public Health said the homes would be an \"integral part\" of the policy.\nDr Brink confirmed one of the two badly affected facilities had \"completely resolved\" its issues, while the second still had six people affected.\nShe reiterated the homes were still \"extremely vulnerable\" to a coronavirus outbreak and Public Health had a \"duty\" to ensure everything they provide is as \"safe as possible\".\nPresident of Health and Social Care Heidi Soulsby emphasised the island's care homes are private companies and the States has no involvement in their running.\nDeputy Soulsby said: \"There is inspections of care homes, but no regulation and that is something that we plan to bring in.\"\nThe introduction of a regulation scheme was being discussed before the pandemic began.", "url": "https://www.bbc.com/news/live/world-europe-guernsey-52528538"}