{"authors": [], "date_download": "2021-08-07 19:28:41", "date_modify": "2021-08-07 19:28:41", "date_publish": "2020-07-20 08:00:00", "description": "News and reaction to the impact of coronavirus on Jersey and other top stories.", "filename": "news_live_world-europe-jersey-53450353_1628364521.html", "image_url": "https://m.files.bbci.co.uk/modules/bbc-morph-news-waf-page-meta/5.1.0/bbc_news_logo.png", "language": "en", "localpath": "D:\\news_set/data/2021/08/06/bbc.com/news_live_world-europe-jersey-53450353_1628364521.html", "title": "Coronavirus: Jersey news and virus updates 20-24 July", "title_page": "Coronavirus: Jersey news and virus updates 20-24 July - BBC News", "title_rss": "NULL", "source_domain": "bbc.com", "maintext": "Dr Ivan Muscat, Jersey's deputy medical officer of health, said there will be \"significant improvement\" on the time it takes to get results from coronavirus testing.\nSpeaking to BBC Radio Jersey about efforts to ramp up PCR or swab testing on the island, he said his department is \"trying to improve efficiency of both the transport system and the IT system for feeding back results not just to Jersey but then to the individuals concerned\".\nGetty Images Copyright: Getty Images\nOn-island and at scale testing is also being brought in, which Dr Muscat said will allow the processing of 1,300 tests every eight hours.\nAs there would be two or more shifts a day, there would be an average of 2,600 tests a day with a turn-around time that could be as little as five to six hours, he said.\nThe result will go out electronically \"there and then\" in what Dr Muscat called a \"significant improvement on where we are\".", "url": "https://www.bbc.com/news/live/world-europe-jersey-53450353"}