{"authors": [], "date_download": "2021-08-08 15:10:17", "date_modify": "2021-08-08 15:10:17", "date_publish": "2020-10-26 13:16:19", "description": "Irish president says concerns about the controversial bill must be addressed.", "filename": "news_world-europe-54685379_1628435417.html", "image_url": "https://ichef.bbci.co.uk/news/1024/branded_news/F37F/production/_94953326_tuam.jpg", "language": "en", "localpath": "D:\\news_set/data/2021/08/06/bbc.com/news_world-europe-54685379_1628435417.html", "title": "Mother and baby homes: Michael D Higgins signs bill into law", "title_page": "Mother and baby homes: Michael D Higgins signs bill into law - BBC News", "title_rss": "NULL", "source_domain": "bbc.com", "maintext": "But campaigners on behalf of the mothers and their children have expressed fears they will not be able to access their records if they are sealed.", "url": "https://www.bbc.com/news/world-europe-54685379"}