{"authors": [], "date_download": "2021-08-06 20:21:18", "date_modify": "2021-08-06 20:21:18", "date_publish": "2020-02-19 20:06:05", "description": "The note asks the reader to \"communicate\" with John Stapleford, dated from 1938.", "filename": "news_world-europe-jersey-51565112_1628281278.html", "image_url": "https://ichef.bbci.co.uk/news/1024/branded_news/629E/production/_110964252_messagejersey.jpg", "language": "en", "localpath": "D:\\news_set/data/2021/08/06/bbc.com/news_world-europe-jersey-51565112_1628281278.html", "title": "Message in a bottle 'returns' to Jersey beach 82 years later", "title_page": "Message in a bottle 'returns' to Jersey beach 82 years later - BBC News", "title_rss": "NULL", "source_domain": "bbc.com", "maintext": "People investigating the bottle said that led them to believe the note had originated from the island and they had guessed it was sent by Mr Stapleford, who was curious about whether anyone would find it.", "url": "https://www.bbc.com/news/world-europe-jersey-51565112"}