{"authors": [], "date_download": "2021-08-08 19:24:06", "date_modify": "2021-08-08 19:24:06", "date_publish": "2020-08-11 11:13:49", "description": "Residents say more people from France are arriving, despite being moved to amber risk.", "filename": "news_world-europe-jersey-53733155_1628450646.html", "image_url": "https://ichef.bbci.co.uk/news/1024/branded_news/1DEA/production/_113885670_ecrehousstockshots2020.jpg", "language": "en", "localpath": "D:\\news_set/data/2021/08/06/bbc.com/news_world-europe-jersey-53733155_1628450646.html", "title": "Coronavirus: Fears over arrivals on Jersey's Ecrehous islands", "title_page": "Coronavirus: Fears over arrivals on Jersey's Ecrehous islands - BBC News", "title_rss": "NULL", "source_domain": "bbc.com", "maintext": "\"You could say that in some awful sense you are dealing with a Russian roulette situation, because you just need one or two of those people coming in from Brittany or Normandy and you know, you just need one person to spread something,\" he said.", "url": "https://www.bbc.com/news/world-europe-jersey-53733155"}