{"authors": [], "date_download": "2021-08-08 05:46:37", "date_modify": "2021-08-08 05:46:37", "date_publish": "2020-09-14 08:00:00", "description": "News and reaction to the impact of coronavirus on the Bailiwick of Guernsey and other top stories.", "filename": "news_live_world-europe-guernsey-54130550_1628401597.html", "image_url": "https://m.files.bbci.co.uk/modules/bbc-morph-news-waf-page-meta/5.1.0/bbc_news_logo.png", "language": "en", "localpath": "D:\\news_set/data/2021/08/06/bbc.com/news_live_world-europe-guernsey-54130550_1628401597.html", "title": "Coronavirus: Guernsey updates and other news 14-18 September", "title_page": "Coronavirus: Guernsey updates and other news 14-18 September - BBC News", "title_rss": "NULL", "source_domain": "bbc.com", "maintext": "The Guernsey Fishermens' Association are concerned the UK may try to use the channel fishing rights as part of the Brexit negotiations with the EU.\nGuernsey currently has an agreement with France until the end of the year to allow certain fishing rights to French fishermen. The agreement aims to protect the existing agreement during the ongoing Brexit negotiations.\nGetty Images Copyright: Getty Images\nChairman of the group Barry Paint told Radio Guernsey the speculations seems to have come out of nowhere.\n\"I'm so surprised that everything has happened so quickly because that wasn't in the arrangements, and bear in mind that the English government gave us control of the 12-mile limit only this year.\n\"So what's happening? I really don't know myself. But if this is true, and there is never smoke without fire, this isn't playing the game, this is just not playing the game.\"", "url": "https://www.bbc.com/news/live/world-europe-guernsey-54130550"}